README.md
setup.py
liteorm/__init__.py
liteorm/engine.py
liteorm/factory.py
liteorm/info.py
liteorm/mapper.py
liteorm/orm.py
liteorm/service.py
liteorm/util.py
liteorm.egg-info/PKG-INFO
liteorm.egg-info/SOURCES.txt
liteorm.egg-info/dependency_links.txt
liteorm.egg-info/not-zip-safe
liteorm.egg-info/requires.txt
liteorm.egg-info/top_level.txt